[{"type":"Dog","name":"Bradley","adoptionStatus":"Adopted","picture":"","height":14,"weight":75,"color":"White/Blue","bio":"","hypoallergnic":false,"dietary":[],"breed":"Pit Bull Mix","id":"a4b49144-b706-45ce-9237-635b780c51bd"},{"type":"Cat","name":"Pebbles","adoptionStatus":"Adopted","picture":"","height":84,"weight":75,"color":"Calico","bio":"","hypoallergnic":true,"dietary":[],"breed":"Domestic Shorthair Mix","id":"92e604d5-3d7b-4faf-992b-f78038e6ebe8"},{"type":"Dog","name":"Johnny","adoptionStatus":"Adopted","picture":"","height":66,"weight":88,"color":"Blue/White","bio":"","hypoallergnic":true,"dietary":[],"breed":"Pit Bull","id":"9e0fe034-4486-465b-8010-2fc0c1e22d38"},{"type":"Cat","name":"Miso","adoptionStatus":"Adopted","picture":"","height":26,"weight":8,"color":"Brown Tabby/White","bio":"","hypoallergnic":false,"dietary":[],"breed":"Domestic Shorthair Mix","id":"6f825359-633c-4ba9-97c5-10d87a4da6e3"},{"type":"Cat","name":"Lucky Charm","adoptionStatus":"Adopted","picture":"","height":10,"weight":69,"color":"Orange Tabby","bio":"","hypoallergnic":true,"dietary":[],"breed":"Domestic Shorthair Mix","id":"a6fc791a-68c6-4f80-8b4e-9e12611950a0"},{"type":"Dog","name":"Megatron","adoptionStatus":"Adopted","picture":"","height":44,"weight":14,"color":"Red","bio":"","hypoallergnic":true,"dietary":[],"breed":"Dachshund/Chihuahua Shorthair","id":"62454c4a-b34d-4f7b-88ba-0ec6750a5acd"},{"type":"Dog","name":"Moomoo","adoptionStatus":"Adopted","picture":"","height":98,"weight":96,"color":"White/Black","bio":"","hypoallergnic":true,"dietary":[],"breed":"French Bulldog/Pit Bull","id":"623c7ed2-e419-4c08-9338-7c26768e6615"},{"type":"Dog","name":"Lindi","adoptionStatus":"Adopted","picture":"","height":94,"weight":67,"color":"Black/White","bio":"","hypoallergnic":false,"dietary":[],"breed":"Pit Bull Mix","id":"11e3d09f-90a1-477f-bd18-f7474d3bca56"},{"type":"Dog","name":"Church","adoptionStatus":"Adopted","picture":"","height":97,"weight":17,"color":"Brown Brindle","bio":"","hypoallergnic":true,"dietary":[],"breed":"Plott Hound Mix","id":"5fc5b17b-ad9b-4e25-8e31-50ec04038934"},{"type":"Cat","name":"Huncho","adoptionStatus":"Adopted","picture":"","height":85,"weight":47,"color":"White/Brown Tabby","bio":"","hypoallergnic":true,"dietary":[],"breed":"Domestic Shorthair Mix","id":"e829942b-a984-4f0e-be4f-453a1f7459f0"},{"type":"Dog","name":"Calvin","adoptionStatus":"Adopted","picture":"","height":40,"weight":90,"color":"Tan/White","bio":"","hypoallergnic":true,"dietary":[],"breed":"Border Terrier Mix","id":"1a4607db-207d-44aa-834c-31db989562bc"},{"type":"Cat","name":"Sandi","adoptionStatus":"Adopted","picture":"","height":52,"weight":39,"color":"Torbie/White","bio":"","hypoallergnic":false,"dietary":[],"breed":"Domestic Shorthair Mix","id":"f60a62f3-0452-467d-84c4-ae69ea39e88d"},{"type":"Other","name":"Bun Jovi","adoptionStatus":"Adopted","picture":"","height":48,"weight":1,"color":"White","bio":"","hypoallergnic":true,"dietary":[],"breed":"Californian","id":"cdd20035-4f79-4d5a-ac6e-28bb6c649edc"},{"type":"Cat","name":"Lucy","adoptionStatus":"Adopted","picture":"","height":29,"weight":24,"color":"Blue Tabby/White","bio":"","hypoallergnic":true,"dietary":[],"breed":"Domestic Shorthair Mix","id":"3dbebcd2-2a2b-4a66-90de-4f14a4adf57e"},{"type":"Cat","name":"Frida","adoptionStatus":"Adopted","picture":"","height":28,"weight":36,"color":"White/Black","bio":"","hypoallergnic":true,"dietary":[],"breed":"Domestic Shorthair Mix","id":"35e802e3-1dab-487a-acdd-ed15850ab3c8"},{"type":"Cat","name":"Ozzy","adoptionStatus":"Adopted","picture":"","height":43,"weight":61,"color":"Blue Tabby/White","bio":"","hypoallergnic":false,"dietary":[],"breed":"Domestic Medium Hair Mix","id":"fff989cd-38ae-429a-92c3-b33262ed9f7c"},{"type":"Cat","name":"Finnegan","adoptionStatus":"Adopted","picture":"","height":37,"weight":70,"color":"Flame Point","bio":"","hypoallergnic":false,"dietary":[],"breed":"Siamese Mix","id":"2f24fa93-2a4c-437e-a50e-cedceba27048"},{"type":"Dog","name":"Spike","adoptionStatus":"Adopted","picture":"","height":56,"weight":95,"color":"Black/White","bio":"","hypoallergnic":true,"dietary":[],"breed":"Chihuahua Shorthair Mix","id":"ae7e4621-a442-4fb4-9ddc-0e151387b493"},{"type":"Dog","name":"Kash","adoptionStatus":"Adopted","picture":"","height":60,"weight":69,"color":"Black","bio":"","hypoallergnic":false,"dietary":[],"breed":"Chihuahua Shorthair/Pomeranian","id":"56e00717-ac01-471c-adc1-30557c76d6d6"},{"type":"Dog","name":"Cheyenne","adoptionStatus":"Adopted","picture":"","height":33,"weight":75,"color":"Blue/Tan","bio":"","hypoallergnic":false,"dietary":[],"breed":"Dachshund Wirehair/Miniature Poodle","id":"71d43c33-426c-482f-bdd6-5f12f32755ad"},{"type":"Cat","name":"Jorge Mcfly","adoptionStatus":"Adopted","picture":"","height":61,"weight":100,"color":"Black/White","bio":"","hypoallergnic":false,"dietary":[],"breed":"Domestic Shorthair Mix","id":"9778da20-ac1c-468b-b4f2-2ecc21dc5b36"},{"type":"Dog","name":"Sassy","adoptionStatus":"Adopted","picture":"","height":44,"weight":29,"color":"White/Brown","bio":"","hypoallergnic":true,"dietary":[],"breed":"Cairn Terrier Mix","id":"8ca0ba21-513f-4a9b-8007-ec98cd0cf7a8"},{"type":"Cat","name":"Gretchen","adoptionStatus":"Adopted","picture":"","height":43,"weight":14,"color":"Tortie","bio":"","hypoallergnic":false,"dietary":[],"breed":"Domestic Shorthair Mix","id":"56a10bb5-b245-47af-97e7-ee83848049e9"},{"type":"Dog","name":"Theo","adoptionStatus":"Adopted","picture":"","height":90,"weight":68,"color":"Tan/Black","bio":"","hypoallergnic":true,"dietary":[],"breed":"Swedish Vallhund Mix","id":"2d6e4705-6792-464e-b524-7ae9c74f9ba9"},{"type":"Dog","name":"Bessie","adoptionStatus":"Adopted","picture":"","height":57,"weight":72,"color":"White/Brown","bio":"","hypoallergnic":true,"dietary":[],"breed":"Australian Cattle Dog Mix","id":"506c3a62-4ffd-47ef-a807-fde48cd473af"},{"type":"Cat","name":"Fern","adoptionStatus":"Adopted","picture":"","height":21,"weight":87,"color":"Blue Tabby/White","bio":"","hypoallergnic":false,"dietary":[],"breed":"Domestic Shorthair Mix","id":"e8a81f00-6644-4806-9c86-7367b19ba7e8"},{"type":"Dog","name":"Merlin","adoptionStatus":"Adopted","picture":"","height":65,"weight":3,"color":"Blue/White","bio":"","hypoallergnic":false,"dietary":[],"breed":"Pit Bull Mix","id":"c2371d8c-6364-43fb-a1f7-ae1643cd3192"},{"type":"Dog","name":"Shadow","adoptionStatus":"Adopted","picture":"","height":53,"weight":13,"color":"Black","bio":"","hypoallergnic":false,"dietary":[],"breed":"Flat Coat Retriever Mix","id":"71b83967-8946-4fab-9178-eecd1570aa19"},{"type":"Cat","name":"Elsa","adoptionStatus":"Adopted","picture":"","height":68,"weight":32,"color":"Brown Tabby","bio":"","hypoallergnic":true,"dietary":[],"breed":"Domestic Shorthair Mix","id":"9d41cda1-161f-49b1-9279-0099676e07b2"},{"type":"Dog","name":"River","adoptionStatus":"Adopted","picture":"","height":77,"weight":79,"color":"Tan/White","bio":"","hypoallergnic":true,"dietary":[],"breed":"Labrador Retriever Mix","id":"4194f908-49a2-4d1b-bcd8-1a1fbc537b2f"},{"type":"Dog","name":"Pippi","adoptionStatus":"Adopted","picture":"","height":40,"weight":9,"color":"Brown/White","bio":"","hypoallergnic":false,"dietary":[],"breed":"Chihuahua Shorthair Mix","id":"f5213462-0379-49ef-8584-4b3f9f98ad36"},{"type":"Dog","name":"Max","adoptionStatus":"Adopted","picture":"","height":10,"weight":62,"color":"Sable","bio":"","hypoallergnic":false,"dietary":[],"breed":"German Shepherd Mix","id":"0d0b4570-3b70-402c-859d-f6c7ca8c3d50"},{"type":"Dog","name":"Bailey","adoptionStatus":"Adopted","picture":"","height":58,"weight":29,"color":"White/Brown","bio":"","hypoallergnic":true,"dietary":[],"breed":"Pit Bull/Labrador Retriever","id":"a14a7550-66af-4d8f-8897-f0e63d80b0c1"},{"type":"Cat","name":"Chester","adoptionStatus":"Adopted","picture":"","height":92,"weight":44,"color":"Black Tabby","bio":"","hypoallergnic":true,"dietary":[],"breed":"Domestic Shorthair Mix","id":"25413a5f-bd86-429d-b25e-a38056e582d2"},{"type":"Dog","name":"Dolly","adoptionStatus":"Adopted","picture":"","height":96,"weight":23,"color":"Tan/White","bio":"","hypoallergnic":false,"dietary":[],"breed":"Beagle Mix","id":"f2e18a33-c9dc-4b52-a63b-9866790bec2e"},{"type":"Cat","name":"Oliver","adoptionStatus":"Adopted","picture":"","height":50,"weight":15,"color":"Orange Tabby","bio":"","hypoallergnic":false,"dietary":[],"breed":"Domestic Shorthair Mix","id":"f2a17d19-594c-4b6b-a309-7f47df02d60f"},{"type":"Dog","name":"Ryker","adoptionStatus":"Adopted","picture":"","height":68,"weight":70,"color":"Brown/White","bio":"","hypoallergnic":false,"dietary":[],"breed":"Pit Bull Mix","id":"680fdaa4-7833-408f-be0b-01ac0851bf5a"},{"type":"Dog","name":"Rosie","adoptionStatus":"Adopted","picture":"","height":57,"weight":59,"color":"Blue","bio":"","hypoallergnic":true,"dietary":[],"breed":"Pit Bull Mix","id":"f85bf949-a56c-4f24-9d7d-142fac8276bb"},{"type":"Cat","name":"Fern","adoptionStatus":"Adopted","picture":"","height":49,"weight":63,"color":"Calico","bio":"","hypoallergnic":true,"dietary":[],"breed":"Domestic Shorthair","id":"ed065e3b-8b7e-4637-ba28-075712326f37"},{"type":"Dog","name":"Ivy","adoptionStatus":"Adopted","picture":"","height":64,"weight":7,"color":"Blue","bio":"","hypoallergnic":false,"dietary":[],"breed":"Blue Lacy/Australian Kelpie","id":"09c5a4f1-a36a-4981-b63d-f93062d4c002"},{"type":"Dog","name":"Olive","adoptionStatus":"Adopted","picture":"","height":74,"weight":2,"color":"Brown Brindle","bio":"","hypoallergnic":true,"dietary":[],"breed":"Mastiff Mix","id":"459c0f13-6314-48a5-aac0-9121dc6da399"},{"type":"Dog","name":"Molly","adoptionStatus":"Adopted","picture":"","height":48,"weight":17,"color":"White","bio":"","hypoallergnic":false,"dietary":[],"breed":"Yorkshire Terrier/Chihuahua Shorthair","id":"71fe89ef-56b7-4e0b-ad23-1f3af613355f"},{"type":"Dog","name":"Promise","adoptionStatus":"Adopted","picture":"","height":70,"weight":6,"color":"Yellow","bio":"","hypoallergnic":false,"dietary":[],"breed":"Labrador Retriever Mix","id":"0a4de762-3093-4d52-a6bc-395ed1f24c92"},{"type":"Dog","name":"Lucy","adoptionStatus":"Adopted","picture":"","height":48,"weight":3,"color":"White","bio":"","hypoallergnic":true,"dietary":[],"breed":"Maltese Mix","id":"e509f44b-88ae-45cc-a367-828089f27335"},{"type":"Cat","name":"Cinnamon","adoptionStatus":"Adopted","picture":"","height":67,"weight":32,"color":"Brown Tabby","bio":"","hypoallergnic":false,"dietary":[],"breed":"Domestic Shorthair Mix","id":"2bfd3cef-1d32-413c-ba2d-cba9ae0050c3"},{"type":"Dog","name":"Lily","adoptionStatus":"Adopted","picture":"","height":84,"weight":76,"color":"Black/White","bio":"","hypoallergnic":false,"dietary":[],"breed":"Border Collie/Labrador Retriever","id":"3c260afb-2384-4718-9187-33bce1716c59"},{"type":"Dog","name":"Ripley","adoptionStatus":"Adopted","picture":"","height":10,"weight":92,"color":"Tan/White","bio":"","hypoallergnic":false,"dietary":[],"breed":"Labrador Retriever Mix","id":"d17fe248-580d-4eee-85a5-fb9d7dcdb67a"},{"type":"Dog","name":"Lobo","adoptionStatus":"Adopted","picture":"","height":72,"weight":34,"color":"Black/Tricolor","bio":"","hypoallergnic":false,"dietary":[],"breed":"Australian Shepherd Mix","id":"ccdac17d-0fa9-4e7b-94b0-1020e326f1e0"},{"type":"Dog","name":"Jaqueline","adoptionStatus":"Adopted","picture":"","height":68,"weight":54,"color":"Red","bio":"","hypoallergnic":false,"dietary":[],"breed":"Staffordshire Mix","id":"27e17e81-fa20-41e2-aa03-fd0444b7eab5"},{"type":"Cat","name":"Marvin","adoptionStatus":"Adopted","picture":"","height":48,"weight":91,"color":"Brown Tabby","bio":"","hypoallergnic":true,"dietary":[],"breed":"Domestic Shorthair Mix","id":"8a94e44b-8780-492a-8b36-2dc7dc5c6041"},{"type":"Dog","name":"Sheldon","adoptionStatus":"Adopted","picture":"","height":19,"weight":22,"color":"Tricolor","bio":"","hypoallergnic":true,"dietary":[],"breed":"Cardigan Welsh Corgi Mix","id":"757cee4a-6f29-4168-b30b-9595767e46b1"},{"type":"Dog","name":"Kane","adoptionStatus":"Adopted","picture":"","height":30,"weight":82,"color":"Black/White","bio":"","hypoallergnic":true,"dietary":[],"breed":"Labrador Retriever/Pit Bull","id":"d1c02b29-68ed-45ce-b7f5-b48e25249e0a"},{"type":"Cat","name":"Kitten","adoptionStatus":"Adopted","picture":"","height":90,"weight":10,"color":"Brown Tabby","bio":"","hypoallergnic":false,"dietary":[],"breed":"Domestic Shorthair Mix","id":"56f9b226-6106-4411-b0d9-947aa4845060"},{"type":"Cat","name":"Liam","adoptionStatus":"Adopted","picture":"","height":51,"weight":24,"color":"Blue/White","bio":"","hypoallergnic":false,"dietary":[],"breed":"Domestic Longhair Mix","id":"9bf0c554-c2f4-46d8-a6ca-bc35930cc5a7"},{"type":"Dog","name":"Alfie","adoptionStatus":"Adopted","picture":"","height":68,"weight":64,"color":"Cream/Gray","bio":"","hypoallergnic":false,"dietary":[],"breed":"Soft Coated Wheaten Terrier Mix","id":"d2eea767-a08c-4fc7-87b3-d03249969f0e"},{"type":"Dog","name":"Shades","adoptionStatus":"Adopted","picture":"","height":10,"weight":66,"color":"Black/White","bio":"","hypoallergnic":false,"dietary":[],"breed":"Labrador Retriever Mix","id":"3281f657-0c6a-49f1-9775-266660d4521a"},{"type":"Dog","name":"Penny","adoptionStatus":"Adopted","picture":"","height":76,"weight":71,"color":"Buff","bio":"","hypoallergnic":false,"dietary":[],"breed":"Chihuahua Shorthair Mix","id":"81a042ef-f0e3-4cf1-a4ad-0da3880347d1"},{"type":"Dog","name":"Ginger","adoptionStatus":"Adopted","picture":"","height":32,"weight":36,"color":"Red/White","bio":"","hypoallergnic":false,"dietary":[],"breed":"Chihuahua Shorthair Mix","id":"04c7dfa1-e39b-4aae-b8bd-cb33c5390a13"},{"type":"Dog","name":"Lolly","adoptionStatus":"Adopted","picture":"","height":42,"weight":57,"color":"Brown Brindle","bio":"","hypoallergnic":false,"dietary":[],"breed":"Labrador Retriever Mix","id":"9d8fe09b-591b-4290-b361-ed318fa93163"},{"type":"Dog","name":"Sheila","adoptionStatus":"Adopted","picture":"","height":94,"weight":8,"color":"Brown/Black","bio":"","hypoallergnic":false,"dietary":[],"breed":"German Shepherd Mix","id":"63ea39db-ecaa-4a34-9386-5f22a1e6f10b"},{"type":"Dog","name":"Rocket","adoptionStatus":"Adopted","picture":"","height":20,"weight":75,"color":"Tricolor","bio":"","hypoallergnic":false,"dietary":[],"breed":"Chihuahua Shorthair Mix","id":"fb8c3ded-4387-4140-90f5-0c8f1b235c64"},{"type":"Dog","name":"Tucker","adoptionStatus":"Adopted","picture":"","height":51,"weight":32,"color":"Brown/White","bio":"","hypoallergnic":false,"dietary":[],"breed":"Labrador Retriever Mix","id":"af736010-72db-4194-9281-551e385f44be"},{"type":"Cat","name":"Sugar","adoptionStatus":"Adopted","picture":"","height":53,"weight":63,"color":"Black","bio":"","hypoallergnic":false,"dietary":[],"breed":"Domestic Shorthair Mix","id":"49aa31d6-70e2-4845-80b8-a5f2e17040d2"},{"type":"Dog","name":"Chula","adoptionStatus":"Adopted","picture":"","height":24,"weight":45,"color":"Tan","bio":"","hypoallergnic":false,"dietary":[],"breed":"Chihuahua Shorthair/Dachshund","id":"36f86cc6-c13f-441e-b4de-76e4058dfae1"},{"type":"Other","name":"Colossus","adoptionStatus":"Adopted","picture":"","height":81,"weight":4,"color":"Gray","bio":"","hypoallergnic":true,"dietary":[],"breed":"Chinchilla-Stnd Mix","id":"33d57294-8fc0-438c-b567-25fa1f2430c7"},{"type":"Dog","name":"Aria","adoptionStatus":"Adopted","picture":"","height":89,"weight":51,"color":"White/Black","bio":"","hypoallergnic":false,"dietary":[],"breed":"Cardigan Welsh Corgi/English Setter","id":"ad6faba0-d7e2-4c4d-8f77-55822b63c8d9"},{"type":"Cat","name":"Captamerica","adoptionStatus":"Adopted","picture":"","height":72,"weight":10,"color":"Blue/White","bio":"","hypoallergnic":true,"dietary":[],"breed":"Domestic Shorthair Mix","id":"dca4f3df-88af-4dde-9929-2ebf2822fbb6"},{"type":"Dog","name":"Oreo","adoptionStatus":"Adopted","picture":"","height":55,"weight":23,"color":"Black/White","bio":"","hypoallergnic":true,"dietary":[],"breed":"Border Collie Mix","id":"6db2f6b5-e74c-4375-b218-1bf99c7ff02c"},{"type":"Cat","name":"Bacon","adoptionStatus":"Adopted","picture":"","height":30,"weight":87,"color":"Blue","bio":"","hypoallergnic":false,"dietary":[],"breed":"Domestic Shorthair Mix","id":"ac7f7ccf-e83f-41dc-877a-fcf7f259c880"},{"type":"Cat","name":"Winnie","adoptionStatus":"Adopted","picture":"","height":90,"weight":28,"color":"Blue","bio":"","hypoallergnic":false,"dietary":[],"breed":"Russian Blue Mix","id":"95af852b-c880-477b-9f2b-f2df4b8172bf"},{"type":"Cat","name":"Smoke","adoptionStatus":"Adopted","picture":"","height":31,"weight":84,"color":"Blue","bio":"","hypoallergnic":true,"dietary":[],"breed":"Russian Blue Mix","id":"7dd9f327-3f49-4342-8835-8defa1b62106"},{"type":"Cat","name":"Pepper","adoptionStatus":"Adopted","picture":"","height":26,"weight":5,"color":"Black/White","bio":"","hypoallergnic":true,"dietary":[],"breed":"Domestic Shorthair Mix","id":"0080e596-eb18-4c70-99ee-e399d00da7bd"},{"type":"Cat","name":"Mittens","adoptionStatus":"Adopted","picture":"","height":53,"weight":50,"color":"Brown Tabby/White","bio":"","hypoallergnic":true,"dietary":[],"breed":"Domestic Shorthair Mix","id":"36cd36df-3af3-4292-be86-455a16e137e2"},{"type":"Cat","name":"Luke","adoptionStatus":"Adopted","picture":"","height":52,"weight":39,"color":"Black/White","bio":"","hypoallergnic":true,"dietary":[],"breed":"Domestic Shorthair Mix","id":"a67db324-40a2-4602-843a-d4470bd30f19"},{"type":"Cat","name":"Shazie","adoptionStatus":"Adopted","picture":"","height":52,"weight":70,"color":"Black Tabby","bio":"","hypoallergnic":false,"dietary":[],"breed":"Domestic Medium Hair Mix","id":"8bd99f08-b60e-474c-beea-1a562e4f35f9"},{"type":"Dog","name":"Kyra","adoptionStatus":"Adopted","picture":"","height":54,"weight":1,"color":"Fawn/White","bio":"","hypoallergnic":true,"dietary":[],"breed":"Pit Bull Mix","id":"23cc71b7-be8d-4d6d-a5a8-b43b70d278d4"},{"type":"Cat","name":"Moe","adoptionStatus":"Adopted","picture":"","height":40,"weight":22,"color":"Brown Tabby/White","bio":"","hypoallergnic":true,"dietary":[],"breed":"Domestic Shorthair Mix","id":"b2a40396-7184-42a6-a054-85d768fc1865"},{"type":"Dog","name":"Daisy","adoptionStatus":"Adopted","picture":"","height":10,"weight":78,"color":"Tan/White","bio":"","hypoallergnic":false,"dietary":[],"breed":"Chihuahua Shorthair Mix","id":"94d340e1-aa24-46ae-a7dd-9524a5f6b054"},{"type":"Cat","name":"Max","adoptionStatus":"Adopted","picture":"","height":90,"weight":23,"color":"Brown Tabby","bio":"","hypoallergnic":false,"dietary":[],"breed":"Domestic Shorthair Mix","id":"dd8514bc-f413-438d-8b89-9d4c4074cae0"},{"type":"Dog","name":"Brody","adoptionStatus":"Adopted","picture":"","height":40,"weight":12,"color":"White/Brown Brindle","bio":"","hypoallergnic":false,"dietary":[],"breed":"Parson Russell Terrier Mix","id":"485fc8e2-88bf-47e3-9288-4cef0d8d36e5"},{"type":"Dog","name":"Lucky","adoptionStatus":"Adopted","picture":"","height":93,"weight":31,"color":"White","bio":"","hypoallergnic":true,"dietary":[],"breed":"Miniature Poodle Mix","id":"d798e781-1c0c-4252-ad0f-af25ed3a4aca"},{"type":"Dog","name":"Bear","adoptionStatus":"Adopted","picture":"","height":12,"weight":18,"color":"Black","bio":"","hypoallergnic":false,"dietary":[],"breed":"Flat Coat Retriever Mix","id":"6f39c76b-ccf0-4117-b096-9fd10bcfa7a0"},{"type":"Dog","name":"Quill","adoptionStatus":"Adopted","picture":"","height":12,"weight":56,"color":"White/Black","bio":"","hypoallergnic":false,"dietary":[],"breed":"Labrador Retriever Mix","id":"4f3b473c-d8d5-4f01-9820-79b076125a78"},{"type":"Cat","name":"Pumpkin","adoptionStatus":"Fostered","picture":"","height":52,"weight":95,"color":"Orange Tabby","bio":"","hypoallergnic":true,"dietary":[],"breed":"Domestic Medium Hair Mix","id":"153a1e1b-1fa3-49c0-bdeb-e50a4e4ca9c6"},{"type":"Dog","name":"Luke","adoptionStatus":"Fostered","picture":"","height":17,"weight":77,"color":"Tan/Black","bio":"","hypoallergnic":true,"dietary":[],"breed":"Labrador Retriever/Beagle","id":"70f27d79-6987-40b1-9861-bd7cf5f33450"},{"type":"Dog","name":"Ittybitty","adoptionStatus":"Fostered","picture":"","height":74,"weight":71,"color":"Black/White","bio":"","hypoallergnic":true,"dietary":[],"breed":"Pit Bull Mix","id":"98a89e2c-1409-48b2-bf33-c873bd46c304"},{"type":"Dog","name":"Benji","adoptionStatus":"Fostered","picture":"","height":17,"weight":43,"color":"Tan","bio":"","hypoallergnic":true,"dietary":[],"breed":"Border Terrier Mix","id":"6884270d-1e5f-4653-89ac-9dde54914b2b"},{"type":"Dog","name":"Rose","adoptionStatus":"Fostered","picture":"","height":67,"weight":24,"color":"Yellow","bio":"","hypoallergnic":false,"dietary":[],"breed":"Labrador Retriever/Jack Russell Terrier","id":"8b1a0a2f-385f-4381-8d59-9ffd16340b05"},{"type":"Cat","name":"Shakti","adoptionStatus":"Fostered","picture":"","height":41,"weight":21,"color":"Blue/White","bio":"","hypoallergnic":true,"dietary":[],"breed":"Domestic Shorthair Mix","id":"da0c48c5-3640-4f63-81bc-58d0263877c2"},{"type":"Cat","name":"Toots","adoptionStatus":"Fostered","picture":"","height":56,"weight":55,"color":"Blue Tabby","bio":"","hypoallergnic":true,"dietary":[],"breed":"Domestic Shorthair Mix","id":"70a274b4-9263-4b8c-a071-5018ee21a6b5"},{"type":"Dog","name":"Boone","adoptionStatus":"Fostered","picture":"","height":10,"weight":63,"color":"Liver/White","bio":"","hypoallergnic":true,"dietary":[],"breed":"English Springer Spaniel Mix","id":"d36079ad-3245-40d3-b69a-eae514c282c7"},{"type":"Dog","name":"Ruby","adoptionStatus":"Fostered","picture":"","height":62,"weight":72,"color":"Brown Brindle","bio":"","hypoallergnic":true,"dietary":[],"breed":"Catahoula/Labrador Retriever","id":"3ede75c4-ce97-4068-8206-5da6b56eb48a"},{"type":"Dog","name":"White Boy","adoptionStatus":"Fostered","picture":"","height":31,"weight":24,"color":"White/Black","bio":"","hypoallergnic":true,"dietary":[],"breed":"Pit Bull Mix","id":"bca599c2-c662-4218-9fb8-79b191c125a8"},{"type":"Dog","name":"Gio","adoptionStatus":"Fostered","picture":"","height":80,"weight":86,"color":"Red/Tan","bio":"","hypoallergnic":false,"dietary":[],"breed":"Chihuahua Shorthair Mix","id":"245c9423-ecf8-4675-96d2-8ebd8bd3ec57"},{"type":"Cat","name":"Jolie","adoptionStatus":"Fostered","picture":"","height":30,"weight":40,"color":"Brown Tabby/White","bio":"","hypoallergnic":false,"dietary":[],"breed":"Domestic Shorthair Mix","id":"bbdbc6f2-461f-4eab-bf04-82881fc2073f"},{"type":"Dog","name":"Yoshi","adoptionStatus":"Fostered","picture":"","height":73,"weight":75,"color":"Blue/White","bio":"","hypoallergnic":true,"dietary":[],"breed":"Pit Bull Mix","id":"79033d46-fdbc-4a6d-bf30-43edb9072a49"},{"type":"Dog","name":"Toby","adoptionStatus":"Fostered","picture":"","height":20,"weight":28,"color":"Cream","bio":"","hypoallergnic":false,"dietary":[],"breed":"Chihuahua Longhair Mix","id":"cd173e87-2b46-4885-a37f-ec09b2e69ff8"},{"type":"Dog","name":"Charlie","adoptionStatus":"Fostered","picture":"","height":10,"weight":89,"color":"White/Brown","bio":"","hypoallergnic":false,"dietary":[],"breed":"Treeing Walker Coonhound Mix","id":"595e8d38-f954-461a-8e44-af64d0383255"},{"type":"Cat","name":"Stella Luna","adoptionStatus":"Fostered","picture":"","height":45,"weight":77,"color":"Black/White","bio":"","hypoallergnic":true,"dietary":[],"breed":"Domestic Medium Hair Mix","id":"9c677e5c-1a8d-40f8-b47d-af3a6c241b55"},{"type":"Dog","name":"Luna","adoptionStatus":"Fostered","picture":"","height":46,"weight":8,"color":"Black/White","bio":"","hypoallergnic":false,"dietary":[],"breed":"Siberian Husky Mix","id":"99d67725-f784-4703-8bd8-3b808c78aa72"},{"type":"Cat","name":"Lucy","adoptionStatus":"Fostered","picture":"","height":39,"weight":30,"color":"Tortie","bio":"","hypoallergnic":false,"dietary":[],"breed":"Domestic Shorthair Mix","id":"d82fb1e1-505a-49cc-8d66-8816c5b80ef6"},{"type":"Dog","name":"Nala","adoptionStatus":"Fostered","picture":"","height":38,"weight":4,"color":"Black/White","bio":"","hypoallergnic":true,"dietary":[],"breed":"Cocker Spaniel Mix","id":"0629031f-940f-4b1f-aacd-f011fee61760"},{"type":"Dog","name":"Preciosa","adoptionStatus":"Fostered","picture":"","height":100,"weight":0,"color":"Black/Tan","bio":"","hypoallergnic":false,"dietary":[],"breed":"Chihuahua Shorthair Mix","id":"5589e183-7222-4dc1-97c5-bba35919ab2e"},{"type":"Dog","name":"Sandy","adoptionStatus":"Fostered","picture":"","height":19,"weight":93,"color":"White","bio":"","hypoallergnic":true,"dietary":[],"breed":"Miniature Schnauzer/Miniature Poodle","id":"8bf2eb56-d6e3-4c82-b109-3a808019b13a"},{"type":"Dog","name":"Shy","adoptionStatus":"Fostered","picture":"","height":23,"weight":59,"color":"Black","bio":"","hypoallergnic":true,"dietary":[],"breed":"Labrador Retriever Mix","id":"5037b7e7-0cc4-4019-9b4a-87ca98f8ebed"},{"type":"Dog","name":"Luna","adoptionStatus":"Fostered","picture":"","height":66,"weight":42,"color":"Brown/White","bio":"","hypoallergnic":false,"dietary":[],"breed":"Labrador Retriever Mix","id":"9f67abbc-1847-4362-a62d-a0cdafaa9715"},{"type":"Dog","name":"Georgo","adoptionStatus":"Fostered","picture":"","height":49,"weight":35,"color":"Chocolate/Tan","bio":"","hypoallergnic":true,"dietary":[],"breed":"Labrador Retriever Mix","id":"7734929f-9f66-40f4-ae66-6f9777e236d5"},{"type":"Dog","name":"Chucho","adoptionStatus":"Fostered","picture":"","height":19,"weight":2,"color":"Tan/White","bio":"","hypoallergnic":false,"dietary":[],"breed":"Chihuahua Shorthair Mix","id":"1cb5d02f-77e6-4194-afea-5a83dcdfa71f"},{"type":"Cat","name":"Smooches","adoptionStatus":"Fostered","picture":"","height":56,"weight":88,"color":"Black/White","bio":"","hypoallergnic":true,"dietary":[],"breed":"Domestic Shorthair Mix","id":"7ce0c0a6-5450-4735-9e02-a510742ce7c0"},{"type":"Dog","name":"Shadow","adoptionStatus":"Fostered","picture":"","height":54,"weight":83,"color":"Black","bio":"","hypoallergnic":false,"dietary":[],"breed":"German Shepherd","id":"910d42d2-dff5-4c84-b01c-29da5c56a8d9"},{"type":"Dog","name":"Sargento","adoptionStatus":"Fostered","picture":"","height":19,"weight":42,"color":"Red/White","bio":"","hypoallergnic":true,"dietary":[],"breed":"Rhod Ridgeback Mix","id":"f82f177a-ecf7-401e-a46a-d7af4d7d1962"},{"type":"Cat","name":"Mia","adoptionStatus":"Fostered","picture":"","height":85,"weight":80,"color":"Tortie Point","bio":"","hypoallergnic":true,"dietary":[],"breed":"Siamese Mix","id":"b6cf20ac-5916-4a84-87d4-775b5f500be2"},{"type":"Dog","name":"Rosco","adoptionStatus":"Fostered","picture":"","height":97,"weight":99,"color":"Red/White","bio":"","hypoallergnic":false,"dietary":[],"breed":"Chihuahua Shorthair Mix","id":"5ec712ab-29d6-44cd-8910-b0867b415f92"},{"type":"Dog","name":"Canela","adoptionStatus":"Fostered","picture":"","height":77,"weight":85,"color":"White/Tan","bio":"","hypoallergnic":false,"dietary":[],"breed":"Chihuahua Shorthair","id":"65c86113-9e98-4bcb-ae42-911dde941a84"},{"type":"Cat","name":"Harlem","adoptionStatus":"Fostered","picture":"","height":14,"weight":18,"color":"Orange Tabby","bio":"","hypoallergnic":true,"dietary":[],"breed":"Domestic Shorthair Mix","id":"b5256f06-6d5c-41e9-88ea-7314cafe6ce1"},{"type":"Cat","name":"Miss Rose","adoptionStatus":"Fostered","picture":"","height":70,"weight":72,"color":"Calico","bio":"","hypoallergnic":true,"dietary":[],"breed":"Domestic Shorthair Mix","id":"275a0565-4224-4ddd-9976-d8c58c094b2c"},{"type":"Cat","name":"Loki","adoptionStatus":"Fostered","picture":"","height":31,"weight":6,"color":"Brown Tabby","bio":"","hypoallergnic":false,"dietary":[],"breed":"Domestic Longhair Mix","id":"2a60c5d1-712e-4159-884b-f0f56126222a"},{"type":"Dog","name":"Malo","adoptionStatus":"Fostered","picture":"","height":76,"weight":26,"color":"Black","bio":"","hypoallergnic":true,"dietary":[],"breed":"Labrador Retriever Mix","id":"798ec9ac-3ef5-4e52-a60a-4eb55060ffd1"},{"type":"Dog","name":"Chaco","adoptionStatus":"Fostered","picture":"","height":27,"weight":95,"color":"Black/White","bio":"","hypoallergnic":true,"dietary":[],"breed":"Labrador Retriever Mix","id":"a736c6b1-514e-48bc-9f72-2d70c45957fa"},{"type":"Dog","name":"Scooby","adoptionStatus":"Fostered","picture":"","height":26,"weight":78,"color":"Tan/Black","bio":"","hypoallergnic":false,"dietary":[],"breed":"German Shepherd Mix","id":"db3b550c-a978-4897-9a25-ff69179fbeaf"},{"type":"Dog","name":"Lex","adoptionStatus":"Fostered","picture":"","height":15,"weight":86,"color":"Brown","bio":"","hypoallergnic":true,"dietary":[],"breed":"Boxer Mix","id":"c5be1b21-8d2b-404e-a435-d697e4158def"},{"type":"Cat","name":"Peeta","adoptionStatus":"Fostered","picture":"","height":69,"weight":28,"color":"Orange Tabby","bio":"","hypoallergnic":false,"dietary":[],"breed":"Domestic Shorthair Mix","id":"9efc76d8-3bb6-4ec0-a2ec-6ef48337aa80"},{"type":"Cat","name":"Max","adoptionStatus":"Fostered","picture":"","height":64,"weight":91,"color":"Orange Tabby","bio":"","hypoallergnic":false,"dietary":[],"breed":"Domestic Shorthair Mix","id":"3a1f171b-8aa6-415a-8e89-cc826217dc78"},{"type":"Dog","name":"Coco","adoptionStatus":"Fostered","picture":"","height":39,"weight":22,"color":"White/Brown","bio":"","hypoallergnic":true,"dietary":[],"breed":"Pit Bull Mix","id":"59ff7791-b2f0-4c06-a7d7-7364bfd910df"},{"type":"Cat","name":"Fafali","adoptionStatus":"Fostered","picture":"","height":13,"weight":98,"color":"Tortie","bio":"","hypoallergnic":false,"dietary":[],"breed":"Domestic Shorthair Mix","id":"ff4b4100-ab20-4892-9123-5ec1ad6c7810"},{"type":"Dog","name":"Happy Camper","adoptionStatus":"Available","picture":"","height":40,"weight":40,"color":"Black","bio":"","hypoallergnic":true,"dietary":[],"breed":"Labrador Retriever Mix","id":"e823a84c-ac2a-42a4-97c7-b697f5d14186"},{"type":"Dog","name":"Lucy","adoptionStatus":"Available","picture":"","height":61,"weight":53,"color":"White/Brown","bio":"","hypoallergnic":false,"dietary":[],"breed":"Beagle Mix","id":"7ca3bfb9-7dfb-48a0-8bd7-ea2dcd0da497"},{"type":"Dog","name":"Monday","adoptionStatus":"Available","picture":"","height":16,"weight":79,"color":"White","bio":"","hypoallergnic":true,"dietary":[],"breed":"Miniature Schnauzer Mix","id":"d3d89a74-a3e0-432b-a5e0-a4d872e173dd"},{"type":"Dog","name":"Edgar","adoptionStatus":"Available","picture":"","height":68,"weight":86,"color":"Brown/White","bio":"","hypoallergnic":false,"dietary":[],"breed":"Leonberger Mix","id":"52714810-5fad-4be8-8199-1fc7cd13db70"},{"type":"Dog","name":"Ella","adoptionStatus":"Available","picture":"","height":51,"weight":48,"color":"Brown","bio":"","hypoallergnic":true,"dietary":[],"breed":"Chihuahua Shorthair Mix","id":"c98936d0-4d96-4784-8d3a-add83cda500f"},{"type":"Dog","name":"Arnie","adoptionStatus":"Available","picture":"","height":10,"weight":2,"color":"Tan","bio":"","hypoallergnic":false,"dietary":[],"breed":"Norfolk Terrier Mix","id":"77429c48-4ed5-4910-a65d-d677f6033e3d"},{"type":"Cat","name":"James","adoptionStatus":"Available","picture":"","height":83,"weight":29,"color":"Blue Tabby","bio":"","hypoallergnic":true,"dietary":[],"breed":"Domestic Shorthair Mix","id":"115aa34b-c537-487d-b9a2-363eedf16034"},{"type":"Dog","name":"Valentino","adoptionStatus":"Available","picture":"","height":45,"weight":97,"color":"Black/Tan","bio":"","hypoallergnic":true,"dietary":[],"breed":"Pug/Border Terrier","id":"83038df8-bdf5-435c-8c3a-12e5329e8187"},{"type":"Dog","name":"Fancy","adoptionStatus":"Available","picture":"","height":14,"weight":79,"color":"Black/White","bio":"","hypoallergnic":false,"dietary":[],"breed":"Papillon/Border Collie","id":"7551d8fe-4b8a-4f4f-a8d1-7f7cef03ee21"},{"type":"Dog","name":"Novah","adoptionStatus":"Available","picture":"","height":16,"weight":39,"color":"White","bio":"","hypoallergnic":true,"dietary":[],"breed":"Pit Bull Mix","id":"c478f2dd-454b-467e-9d95-8cb7d59ccb8f"},{"type":"Dog","name":"Pepper","adoptionStatus":"Available","picture":"","height":10,"weight":21,"color":"Black/Tricolor","bio":"","hypoallergnic":false,"dietary":[],"breed":"Soft Coated Wheaten Terrier Mix","id":"77036e1b-c3e9-447e-b174-3682031f289c"},{"type":"Dog","name":"Pepper","adoptionStatus":"Available","picture":"","height":36,"weight":53,"color":"Black/Tricolor","bio":"","hypoallergnic":false,"dietary":[],"breed":"Soft Coated Wheaten Terrier Mix","id":"4802297b-d4fa-40f5-bac5-bb0321fc2ba1"},{"type":"Dog","name":"Truman","adoptionStatus":"Available","picture":"","height":83,"weight":36,"color":"White/Black","bio":"","hypoallergnic":false,"dietary":[],"breed":"Rat Terrier Mix","id":"64df4966-7f22-4722-9fa2-a108a947f766"},{"type":"Dog","name":"Martie","adoptionStatus":"Available","picture":"","height":34,"weight":27,"color":"Tricolor","bio":"","hypoallergnic":false,"dietary":[],"breed":"Chihuahua Shorthair Mix","id":"a57ad546-0718-4b6f-94c2-3d786b7f47fb"},{"type":"Dog","name":"Newt","adoptionStatus":"Available","picture":"","height":19,"weight":52,"color":"Brown Brindle/White","bio":"","hypoallergnic":false,"dietary":[],"breed":"Pit Bull Mix","id":"17621445-df9f-491f-ade8-f44bbdfd2ace"},{"type":"Dog","name":"Patrick","adoptionStatus":"Available","picture":"","height":69,"weight":14,"color":"Brown/Black","bio":"","hypoallergnic":false,"dietary":[],"breed":"Pomeranian Mix","id":"71d8e7b5-9f05-46ab-a98d-4c6e3b3da842"},{"type":"Cat","name":"Davis","adoptionStatus":"Available","picture":"","height":94,"weight":83,"color":"Brown Tabby","bio":"","hypoallergnic":true,"dietary":[],"breed":"Domestic Shorthair Mix","id":"0a1938e1-6e87-46d4-b6a2-af0b2dc215a8"},{"type":"Cat","name":"Preston","adoptionStatus":"Available","picture":"","height":48,"weight":16,"color":"Black/White","bio":"","hypoallergnic":true,"dietary":[],"breed":"Domestic Medium Hair Mix","id":"2739c878-8630-440c-ad2f-c885639f04cf"},{"type":"Cat","name":"Montgomery","adoptionStatus":"Available","picture":"","height":54,"weight":43,"color":"Brown Tabby/White","bio":"","hypoallergnic":false,"dietary":[],"breed":"Domestic Shorthair Mix","id":"7e241159-ff17-4a58-a0b6-28c88f92972d"},{"type":"Dog","name":"Ollie","adoptionStatus":"Available","picture":"","height":82,"weight":52,"color":"Black","bio":"","hypoallergnic":false,"dietary":[],"breed":"Australian Cattle Dog/Labrador Retriever","id":"8d117a27-7bf4-42ee-84bb-1b34cdac160f"},{"type":"Dog","name":"Meryl","adoptionStatus":"Available","picture":"","height":66,"weight":31,"color":"Brown Brindle/White","bio":"","hypoallergnic":true,"dietary":[],"breed":"Pit Bull Mix","id":"05677a65-4d3c-42bd-9e37-613686e37299"},{"type":"Dog","name":"Minnie","adoptionStatus":"Available","picture":"","height":15,"weight":8,"color":"Blue/Tan","bio":"","hypoallergnic":true,"dietary":[],"breed":"Chihuahua Shorthair Mix","id":"586f5571-c7f4-49c2-bc9c-5acffebcc5ef"},{"type":"Cat","name":"Bumble","adoptionStatus":"Available","picture":"","height":59,"weight":74,"color":"Seal Point","bio":"","hypoallergnic":false,"dietary":[],"breed":"Siamese","id":"40ac079f-0239-4b61-b90b-8cd733a5ef43"},{"type":"Dog","name":"Vinnie","adoptionStatus":"Available","picture":"","height":41,"weight":99,"color":"Tan/White","bio":"","hypoallergnic":true,"dietary":[],"breed":"Pit Bull Mix","id":"a0d43895-8b2a-4fcb-8935-1173f245d676"},{"type":"Cat","name":"Jasmine","adoptionStatus":"Available","picture":"","height":66,"weight":22,"color":"Orange Tabby/White","bio":"","hypoallergnic":false,"dietary":[],"breed":"Domestic Shorthair Mix","id":"438bc345-86e6-45f8-b033-8e70dd5190e7"},{"type":"Cat","name":"Willow","adoptionStatus":"Available","picture":"","height":43,"weight":61,"color":"Black","bio":"","hypoallergnic":false,"dietary":[],"breed":"Domestic Longhair Mix","id":"a355b77d-c140-4ef4-a35e-c796f9e8d99f"},{"type":"Dog","name":"Brie","adoptionStatus":"Available","picture":"","height":50,"weight":42,"color":"Brown Brindle/White","bio":"","hypoallergnic":true,"dietary":[],"breed":"Greyhound Mix","id":"d158d732-869f-4be3-a17e-c6e206f0fa03"},{"type":"Cat","name":"Lana","adoptionStatus":"Available","picture":"","height":47,"weight":60,"color":"White/Brown Tabby","bio":"","hypoallergnic":true,"dietary":[],"breed":"Domestic Shorthair Mix","id":"2abe262c-b183-40da-92d9-3396f876ea0f"},{"type":"Cat","name":"Glenn","adoptionStatus":"Available","picture":"","height":98,"weight":14,"color":"Blue Tabby/White","bio":"","hypoallergnic":false,"dietary":[],"breed":"Domestic Shorthair Mix","id":"2b86cc53-c4e5-4689-80a5-1d541984bba4"},{"type":"Dog","name":"Josh","adoptionStatus":"Available","picture":"","height":46,"weight":41,"color":"Black/White","bio":"","hypoallergnic":false,"dietary":[],"breed":"Miniature Pinscher Mix","id":"8eb667de-da4f-4317-85ed-468ef41a53fc"},{"type":"Cat","name":"Oreo","adoptionStatus":"Available","picture":"","height":32,"weight":39,"color":"Lynx Point","bio":"","hypoallergnic":true,"dietary":[],"breed":"Domestic Medium Hair","id":"83c7dac4-2277-4711-9951-036106c69301"},{"type":"Dog","name":"Delilah","adoptionStatus":"Available","picture":"","height":77,"weight":36,"color":"Brown Merle/White","bio":"","hypoallergnic":true,"dietary":[],"breed":"Pit Bull Mix","id":"62147d30-57ce-4510-aa5a-b436108c2237"},{"type":"Cat","name":"Snowflake","adoptionStatus":"Available","picture":"","height":30,"weight":63,"color":"Cream Tabby/White","bio":"","hypoallergnic":true,"dietary":[],"breed":"Domestic Shorthair Mix","id":"cea1422b-5b86-412a-93c4-60aadbbd63a8"},{"type":"Cat","name":"Dora","adoptionStatus":"Available","picture":"","height":23,"weight":54,"color":"Calico","bio":"","hypoallergnic":true,"dietary":[],"breed":"Domestic Shorthair Mix","id":"c9660003-1fac-4e9b-85e3-143f77e37d89"},{"type":"Cat","name":"Cosmo","adoptionStatus":"Available","picture":"","height":24,"weight":9,"color":"Chocolate","bio":"","hypoallergnic":true,"dietary":[],"breed":"Domestic Shorthair Mix","id":"6df45c01-7ed5-4391-8b22-f7ac32a0b8e2"},{"type":"dog","name":"asda","adoptionStatus":"Adopted","image":"C:\\fakepath\\Screenshot_20221101_094557.png","height":"1","weight":"1","color":"asda","bio":"asdas","hypoallergenic":true,"dietary":"asda","breed":"asda","id":"68a9428f-d951-4fb7-bb9b-dd74b892e236"},{"type":"dog","name":"asda","adoptionStatus":"Fostered","image":"C:\\fakepath\\Screenshot_20221101_094557.png","height":1,"weight":1,"color":"asd","bio":"asda","hypoallergenic":true,"dietary":"adas","breed":"asda","id":"35677a44-d751-41e5-8d0a-bdce35b7c053"},{"type":"cat","name":"Cat1","adoptionStatus":"Available","image":"C:\\fakepath\\Screenshot_20221101_052907.png","height":2,"weight":1,"color":"red","bio":"asdadal","hypoallergenic":false,"dietary":"none","breed":"asda","id":"3a640a9b-f820-409b-a060-e9a0dbf5d444"},{"type":"Cat","name":"Rajaj","adoptionStatus":"Adopted","image":"","height":3,"weight":65,"color":"Brown Tabby","bio":"","hypoallergenic":true,"dietary":"[]","breed":"Domestic Shorthair Mix","id":"e9c8d78e-6dab-481f-9257-64b8217a275a"}]